intonatang/__init__.py
intonatang/erps.py
intonatang/intonatang.py
intonatang/intonation_encoding.py
intonatang/intonation_invariance.py
intonatang/intonation_preanalysis.py
intonatang/intonation_stims.py
intonatang/intonation_subject_data.py
intonatang/nonspeech_control_generation.py
intonatang/paper_figures.py
intonatang/pitch_trf.py
intonatang/temporal_receptive_field.py
intonatang/timit.py
intonatang/data/README.md
intonatang/data/pink_noise.mat
intonatang/data/brain_imaging/EC113_brain2D.png
intonatang/data/brain_imaging/EC113_elec_pos2D.mat
intonatang/data/timit/.DS_Store
intonatang/data/timit/fadg0_si1279.phn
intonatang/data/timit/faem0_si2022.phn
intonatang/data/timit/falr0_si1955.phn
intonatang/data/timit/fawf0_si1000.phn
intonatang/data/timit/fbcg1_si1612.phn
intonatang/data/timit/fbcg1_si2242.phn
intonatang/data/timit/fbjl0_si2182.phn
intonatang/data/timit/fbmh0_si1766.phn
intonatang/data/timit/fbmj0_si815.phn
intonatang/data/timit/fcag0_si1503.phn
intonatang/data/timit/fcag0_si1641.phn
intonatang/data/timit/fcaj0_si1479.phn
intonatang/data/timit/fcaj0_si1804.phn
intonatang/data/timit/fceg0_si1878.phn
intonatang/data/timit/fceg0_si618.phn
intonatang/data/timit/fcft0_si1808.phn
intonatang/data/timit/fcft0_si548.phn
intonatang/data/timit/fcjs0_si1607.phn
intonatang/data/timit/fcjs0_si2237.phn
intonatang/data/timit/fcke0_si1111.phn
intonatang/data/timit/fclt0_si2068.phn
intonatang/data/timit/fcmh0_si2084.phn
intonatang/data/timit/fcmh1_si1493.phn
intonatang/data/timit/fcmm0_si1083.phn
intonatang/data/timit/fcmm0_si453.phn
intonatang/data/timit/fcmr0_si1735.phn
intonatang/data/timit/fcmr0_si475.phn
intonatang/data/timit/fcrh0_si1718.phn
intonatang/data/timit/fcrz0_si2053.phn
intonatang/data/timit/fdas1_si2091.phn
intonatang/data/timit/fdaw0_si1406.phn
intonatang/data/timit/fdfb0_si1948.phn
intonatang/data/timit/fdfb0_si2010.phn
intonatang/data/timit/fdhc0_si2189.phn
intonatang/data/timit/fdjh0_si1565.phn
intonatang-2017.7.13.dist-info/DESCRIPTION.rst
intonatang-2017.7.13.dist-info/METADATA
intonatang-2017.7.13.dist-info/RECORD
intonatang-2017.7.13.dist-info/WHEEL
intonatang-2017.7.13.dist-info/metadata.json
intonatang-2017.7.13.dist-info/pbr.json
intonatang-2017.7.13.dist-info/top_level.txt
