Metadata-Version: 2.0
Name: intonatang
Version: 2017.7.13
Summary: Analysis code for speech intonation project
Home-page: UNKNOWN
Author: Claire Tang
Author-email: clairetang6@gmail.com
License: UNKNOWN
Platform: UNKNOWN
Classifier: Intended Audience :: Science/Research
Classifier: Intended Audience :: Developers
Classifier: Intended Audience :: Education
Classifier: Programming Language :: Python :: 2.7
Classifier: Topic :: Scientific/Engineering
Classifier: Topic :: Scientific/Engineering :: Bio-Informatics
Classifier: Topic :: Scientific/Engineering :: Visualization
